odoo/addons/delivery_carrier_preference/README.rst
odoo/addons/delivery_carrier_preference/__init__.py
odoo/addons/delivery_carrier_preference/__manifest__.py
odoo/addons/delivery_carrier_preference/i18n/de.po
odoo/addons/delivery_carrier_preference/i18n/delivery_carrier_preference.pot
odoo/addons/delivery_carrier_preference/models/__init__.py
odoo/addons/delivery_carrier_preference/models/delivery_carrier_preference.py
odoo/addons/delivery_carrier_preference/models/procurement_group.py
odoo/addons/delivery_carrier_preference/models/stock_location_route.py
odoo/addons/delivery_carrier_preference/models/stock_move.py
odoo/addons/delivery_carrier_preference/models/stock_picking.py
odoo/addons/delivery_carrier_preference/readme/CONFIGURE.rst
odoo/addons/delivery_carrier_preference/readme/CONTRIBUTORS.rst
odoo/addons/delivery_carrier_preference/readme/DESCRIPTION.rst
odoo/addons/delivery_carrier_preference/security/ir.model.access.csv
odoo/addons/delivery_carrier_preference/static/description/icon.png
odoo/addons/delivery_carrier_preference/static/description/index.html
odoo/addons/delivery_carrier_preference/tests/__init__.py
odoo/addons/delivery_carrier_preference/tests/test_delivery_carrier_preference.py
odoo/addons/delivery_carrier_preference/views/delivery_carrier_preference.xml
odoo/addons/delivery_carrier_preference/views/stock_location_route.xml
odoo/addons/delivery_carrier_preference/views/stock_move.xml
odoo/addons/delivery_carrier_preference/views/stock_picking.xml
odoo13_addon_delivery_carrier_preference-13.0.1.5.0.dist-info/METADATA
odoo13_addon_delivery_carrier_preference-13.0.1.5.0.dist-info/WHEEL
odoo13_addon_delivery_carrier_preference-13.0.1.5.0.dist-info/top_level.txt
odoo13_addon_delivery_carrier_preference-13.0.1.5.0.dist-info/RECORD
