Metadata-Version: 2.1
Name: odoo13-addon-delivery-carrier-preference
Version: 13.0.1.5.0
Summary: Advanced selection of preferred shipping methods
Home-page: https://github.com/OCA/wms
Author: Camptocamp, Odoo Community Association (OCA)
Author-email: support@odoo-community.org
License: AGPL-3
Platform: UNKNOWN
Classifier: Programming Language :: Python
Classifier: Framework :: Odoo
Classifier: License :: OSI Approved :: GNU Affero General Public License v3
Requires-Python: >=3.5
Requires-Dist: odoo13-addon-product-total-weight-from-packaging
Requires-Dist: odoo13-addon-stock-available-to-promise-release
Requires-Dist: odoo13-addon-stock-picking-group-by-partner-by-carrier
Requires-Dist: odoo (<13.1dev,>=13.0a)
